pycss_lem/__init__.py
pycss_lem/automaticslipcircles.py
pycss_lem/azimuthangle.py
pycss_lem/circleby2ptsradius.py
pycss_lem/create2dsegmentstructure.py
pycss_lem/defineslipcircle.py
pycss_lem/defineswatertable.py
pycss_lem/divideslipintoslices.py
pycss_lem/extractplinefrom2pts.py
pycss_lem/interatefbishopsimpsat.py
pycss_lem/interateffelleniussat.py
pycss_lem/materialboundary.py
pycss_lem/obtainmaxdepthdist.py
pycss_lem/onlyonecircle.py
pycss_lem/plotslice.py
pycss_lem/polyarea.py
pycss_lem/pyCSS.py
pycss_lem/reportslicestructurevalues.py
pycss_lem/sliparcdiscretization.py
pycss_lem/tangentlineatcirclept.py
pycss_lem/terrainsurface.py
pycss_lem/uniquewithtolerance.py
pycss_lem/unitvector.py
pycss_lem/vertprojection2pline.py
pycss_lem-0.1.0.dist-info/METADATA
pycss_lem-0.1.0.dist-info/WHEEL
pycss_lem-0.1.0.dist-info/licenses/LICENSE.md
pycss_lem-0.1.0.dist-info/RECORD
