Metadata-Version: 2.1
Name: pycss-lem
Version: 0.1.0
Summary: 2D slope stability analysis of circular surfaces by the limit equilibrium method (Fellenius and Bishop methods).
Project-URL: Homepage, https://github.com/eamontoyaa/pyCSS
Project-URL: Documentation, https://github.com/eamontoyaa/pyCSS
Author-email: "Exneyder A. Montoya-Araque" <eamontoyaa@gmail.com>, "Suarez-Burgoa, Ludger O" <losuarezb@unal.edu.co>
License-File: LICENSE.md
Classifier: Development Status :: 4 - Beta
Classifier: Intended Audience :: Developers
Classifier: Intended Audience :: Information Technology
Classifier: Intended Audience :: System Administrators
Classifier: License :: OSI Approved :: MIT License
Classifier: Operating System :: OS Independent
Classifier: Programming Language :: Python
Classifier: Programming Language :: Python :: 3
Classifier: Programming Language :: Python :: 3 :: Only
Classifier: Programming Language :: Python :: 3.7
Classifier: Programming Language :: Python :: 3.8
Classifier: Programming Language :: Python :: 3.9
Classifier: Programming Language :: Python :: 3.10
Classifier: Topic :: Software Development
Classifier: Topic :: Software Development :: Libraries
Classifier: Topic :: Software Development :: Libraries :: Python Modules
Requires-Python: >=3.6
Requires-Dist: matplotlib>=1.5.3
Requires-Dist: numpy>=1.14.5
Requires-Dist: scipy>=1.5
